brainseg/__init__.py
brainseg/__main__.py
brainseg/annotation_window.py
brainseg/canvas.py
brainseg/help_window.py
brainseg/image_utils.py
brainseg/intensity_palette.py
brainseg/main.py
brainseg/main_window.py
brainseg/model.py
brainseg/settings_window.py
brainseg/statistics_tracker.py
brainseg/statistics_window.py
brainseg/theme.py
brainseg/worker.py
brainseg_ai-1.5.2.dist-info/licenses/LICENSE
brainseg_ai-1.5.2.dist-info/METADATA
brainseg_ai-1.5.2.dist-info/WHEEL
brainseg_ai-1.5.2.dist-info/entry_points.txt
brainseg_ai-1.5.2.dist-info/top_level.txt
brainseg_ai-1.5.2.dist-info/RECORD
