Metadata-Version: 2.4
Name: brainseg-ai
Version: 1.5.2
Summary: Brain abnormality segmentation application
Author: Md. Rasel Mandol
Requires-Python: >=3.10
License-File: LICENSE
Requires-Dist: torch
Requires-Dist: torchvision
Requires-Dist: segmentation-models-pytorch
Requires-Dist: gradio
Requires-Dist: opencv-python
Requires-Dist: numpy
Requires-Dist: scipy
Requires-Dist: psutil
Requires-Dist: PyQt6
Dynamic: license-file
